isocomp/Compare/IsoformLibrary.py
isocomp/Compare/__init__.py
isocomp/Compare/align_isoforms.py
isocomp/Compare/compare_isoforms_in_cluster.py
isocomp/Compare/filter_comparisons.py
isocomp/Compare/find_unique_isoforms.py
isocomp/Coordinates/Window.py
isocomp/Coordinates/__init__.py
isocomp/Coordinates/create_comparison_windows.py
isocomp/Coordinates/update_source.py
isocomp/__init__.py
isocomp/__main__.py
isocomp/utils/__init__.py
isocomp/utils/configure_logging.py
isocomp/utils/fasta_to_fastq.py
isocomp-0.3.0.dist-info/LICENSE
isocomp-0.3.0.dist-info/METADATA
isocomp-0.3.0.dist-info/WHEEL
isocomp-0.3.0.dist-info/entry_points.txt
isocomp-0.3.0.dist-info/RECORD
