Metadata-Version: 2.1
Name: isocomp
Version: 0.3.0
Summary: 
Author: Yutong Qiu
Author-email: yutongq@andrew.cmu.edu
Requires-Python: >=3.9,<4.0
Classifier: Programming Language :: Python :: 3
Classifier: Programming Language :: Python :: 3.9
Classifier: Programming Language :: Python :: 3.10
Classifier: Programming Language :: Python :: 3.11
Requires-Dist: biopython (>=1.80,<2.0)
Requires-Dist: edlib (>=1.3.9,<2.0.0)
Requires-Dist: numpy (==1.23)
Requires-Dist: pandas (>=1.5.1,<2.0.0)
Requires-Dist: pyranges (>=0.0.120,<0.0.121)
Requires-Dist: pysam (>=0.20.0,<0.21.0)
